pandav/1.ipynb
pandav/2.ipynb
pandav/__init__.py
pandav/display.py
pandav/downloader.py
pandav/pandav.py
pandav/.ipynb_checkpoints/__init__-checkpoint.py
pandav/.ipynb_checkpoints/display-checkpoint.py
pandav-0.1.6.dist-info/LICENSE
pandav-0.1.6.dist-info/METADATA
pandav-0.1.6.dist-info/WHEEL
pandav-0.1.6.dist-info/top_level.txt
pandav-0.1.6.dist-info/RECORD
