Metadata-Version: 2.1
Name: pandav
Version: 0.1.6
Summary: A simple Python module with basic functions
Author: Pubg Lover
Author-email: pubglover2511@gmail.com
Classifier: Programming Language :: Python :: 3
Classifier: License :: OSI Approved :: MIT License
Classifier: Operating System :: OS Independent
Requires-Python: >=3.0
License-File: LICENSE
